cassis/__init__.py
cassis/cas.py
cassis/json.py
cassis/typesystem.py
cassis/util.py
cassis/xmi.py
cassis/resources/__init__.py
cassis/resources/dkpro-core-types.xml
dkpro_cassis-0.10.1.dist-info/licenses/LICENSE
dkpro_cassis-0.10.1.dist-info/METADATA
dkpro_cassis-0.10.1.dist-info/WHEEL
dkpro_cassis-0.10.1.dist-info/top_level.txt
dkpro_cassis-0.10.1.dist-info/RECORD
