Metadata-Version: 2.4
Name: dkpro-cassis
Version: 0.10.1
Summary: UIMA CAS processing library in Python
Author: The DKPro cassis team
Maintainer: Richard Eckart de Castilho
License:                                  Apache License
Project-URL: Homepage, https://dkpro.github.io
Project-URL: Documentation, https://cassis.readthedocs.io
Project-URL: Repository, https://github.com/dkpro/dkpro-cassis
Classifier: Development Status :: 4 - Beta
Classifier: Intended Audience :: Developers
Classifier: Intended Audience :: Science/Research
Classifier: License :: OSI Approved :: Apache Software License
Classifier: Programming Language :: Python :: 3 :: Only
Classifier: Programming Language :: Python :: 3.9
Classifier: Programming Language :: Python :: 3.10
Classifier: Programming Language :: Python :: 3.11
Classifier: Programming Language :: Python :: 3.12
Classifier: Programming Language :: Python :: 3.13
Classifier: Topic :: Software Development :: Libraries
Classifier: Topic :: Scientific/Engineering :: Human Machine Interfaces
Classifier: Topic :: Text Processing :: Linguistic
Requires-Python: >=3.9
License-File: LICENSE
Requires-Dist: lxml~=5.3.1
Requires-Dist: attrs<26,>=21.2
Requires-Dist: sortedcontainers~=2.4
Requires-Dist: toposort~=1.10
Requires-Dist: more-itertools~=10.6
Requires-Dist: deprecation~=2.1
Requires-Dist: importlib_resources~=6.5.2
Provides-Extra: dev
Requires-Dist: pytest~=8.3.5; extra == "dev"
Requires-Dist: pytest-lazy-fixtures~=1.1.2; extra == "dev"
Requires-Dist: pytest-cov~=6.0.0; extra == "dev"
Requires-Dist: tox~=4.24.2; extra == "dev"
Requires-Dist: lxml-asserts~=0.1.2; extra == "dev"
Requires-Dist: codecov~=2.1.13; extra == "dev"
Requires-Dist: rstcheck~=6.2.4; extra == "dev"
Requires-Dist: docutils~=0.21.2; extra == "dev"
Requires-Dist: ruff~=0.9.10; extra == "dev"
Requires-Dist: pip-tools~=7.4.1; extra == "dev"
Provides-Extra: doc
Requires-Dist: sphinx; extra == "doc"
Requires-Dist: sphinx-autodoc-typehints; extra == "doc"
Requires-Dist: sphinx-rtd-theme; extra == "doc"
Requires-Dist: docutils~=0.21.2; extra == "doc"
Dynamic: license-file
